{
  "story":[
		["王都脱出","王都脱出",9,0],
		["神殿の森","神殿の森",10,0],
		["女神の神殿","女神神殿",11,0],
		["神殿を守れ！","神殿を守れ",12,0],
		["残党退治１","残党退治１",12,0],
		["田園の門","田園の門",12,0],
		["住民救出１","住民救出１",14,0],
		["住民救出２","住民救出２",15,0],
		["田園の門攻防戦","田園門攻防",16,0],
		["住民救出３","住民救出３",18,0],
		["狼の巣","狼の巣",15,0],
		["火事場泥棒","火事場泥棒",19,0],
		["謎の魔物","謎の魔物",20,0],
		["砦の戦い","砦の戦い",21,0],
		["王都に続く道","王都に続道",22,0],
		["山賊の隠れ家","山賊の隠家",15,0],
		["深森の大道","深森の大道",20,0],
		["残党退治２","残党退治２",22,0],
		["哀しみの墓地","哀の墓地",23,0],
		["廃都への帰還","廃都帰還",23,0],
		["戦場の群狼","戦場の群狼",24,0],
		["見張り塔","見張り塔",25,0],
		["亡者の鎧","亡者の鎧",26,0],
		["城門の戦い","城門の戦い",28,0],
		["王都奪還","王都奪還",29,0],
		["残党退治３","残党退治３",30,0],
		["竜の狩場","竜の狩場",37,0],
		["炎の竜","炎の竜",34,0],
		["不死の魔物","不死の魔物",42,0],
		["熱砂の戦場","熱砂の戦場",25,0],
		["砂の廃都","砂の廃都",28,0],
		["焦熱のオアシス","熱オアシス",30,0],
		["砂漠に潜む魔物","砂漠潜魔物",33,0],
		["拠点争奪戦・前","拠点奪戦前",36,0],
		["拠点争奪戦・後","拠点奪戦後",40,0],
		["砂漠のサソリ","砂漠サソリ",44,0],
		["オアシスに迫る危機","オアシス危",47,0],
		["二つのピラミッド","２ピラミド",51,0],
		["東の国の港町","東国港町",45,0],
		["風に散る桜","風に散桜",48,0],
		["田を返せ！","田を返せ！",52,0],
		["絶望の城下町","絶望城下町",56,0],
		["風神退治","風神退治",59,0]
  ],
  "challenge":[
		["腕試し","腕試し",0,1],
		["腕試し２","腕試し２",0,1],
		["足止めして倒せ","足止め",0,1],
		["剣と盾","剣と盾1",0,1],
		["杖と弓","杖と弓1",0,1],
		["ラッシュバトル","ラッシュ１",0,1],
		["ベストパートナー","ベスト",0,1],
		["孤独な戦い","孤独な戦１",0,1],
		["孤独な戦い２","孤独な戦２",0,1],
		["毒の沼","毒の沼１",0,1],
		["低コストバトル","低コスト１",0,1],
		["ラッシュバトル２","ラッシュ２"0,2],
		["対空バトル","対空バトル",0,2],
		["ファランクス","ファラ１",0,2],
		["ハイスピードバトル","ﾊｲｽﾋﾟｰﾄﾞ１",0,2],
		["毒の沼２","毒の沼２",0,2],
		["男の戦い","男の戦い１",0,2],
		["女の戦い","女の戦い２",0,2],
		["背水の陣","背水の陣１",0,2],
		["巨大な敵","巨大な敵２",0,2],
		["低コストバトル２","低コスト２",0,3],
		["孤独な戦い２","孤独な戦２",0,3],
		["孤独な戦い３","孤独な戦３",0,3],
		["ラッシュバトル３","ラッシュ３",0,3],
		["ハイスピードバトル２",,"ﾊｲｽﾋﾟｰﾄﾞ２"0,3],
		["毒の沼３","毒の沼３",0,3],
		["シューティングバトル","ｼｭｰﾃｨﾝｸﾞ１",0,3],
		["背水の陣２","背水の陣２",0,3],
		["ファランクス２","ファラ２",0,3],
		["小人バトル","小人１",0,3],
		["魔法大戦","魔法大戦",0,4],
		["男の戦い２","男の戦い２",0,4],
		["女の戦い２","女の戦い２",0,4],
		["ラッシュバトル４","ラッシュ４",0,4],
		["剣と盾２","剣と盾２",0,4],
		["杖と弓２","杖と弓２",0,4],
		["低コストバトル３","低コスト３",0,4],
		["巨大な敵２","巨大な敵２",0,4],
		["小人バトル２","小人２",0,4],
		["小人と巨人","小人巨人１",0,4],
		["背水の陣３","背水の陣３",0,5],
		["男の戦い３","男の戦い３",0,5],
		["女の戦い３","女の戦い３",0,5],
		["ハイスピードバトル３","ﾊｲｽﾋﾟｰﾄﾞ３",0,5],
		["剣と盾３","剣と盾３",0,5],
		["猛毒の霧","猛毒の霧１",0,6],
		["猛毒の霧２","猛毒の霧２",0,6],
		["ファランクス３","ファラ３",0,6],
		["小人と巨人２","小人巨人２",0,6],
		["ボスラッシュ","ボス",0,7],
  ],
  "mission":[
    {
      "空を断つ必殺剣":[
        ["空からの来襲","空の来襲",20,1],
        ["魔界の刺客","魔界の刺客",30,2],
        ["見張り塔防衛","見張塔防衛",40,3],
        ["空の軍勢","空の軍勢",50,5],
        ["砂塵舞う竜退治","砂塵竜退治",70,6],
        ["奥義開眼","奥義開眼",40,4],
        ["空を覆う黒き影","空を覆黒影",50,5],
        ["復讐の剣士","復讐の剣士",100,2]
      ],
      "千鬼夜行":[
        ["千鬼夜行:初級","千鬼:初",15,0],
        ["千鬼夜行:上級","千鬼:上",30,0],
        ["千鬼夜行:極級","千鬼:極",40,0],
        ["千鬼夜行:神級","千鬼:神",70,0]
      ],
      "月曜ミッション":[
        ["黄金の鎧:初級","黄金:初",15,2],
        ["黄金の鎧:中級","黄金:中",24,2],
        ["黄金の鎧:上級","黄金:上",60,3],
        ["黄金の鎧:極級","黄金:極",80,3],
        ["覚醒の宝珠:白き射手","覚醒:射手",90,0]
      ],
      "火曜ミッション":[
				["聖霊救出:初級","聖霊:初",15,2],
				["聖霊救出:中級","聖霊:中",30,3],
				["聖霊救出:上級","聖霊:上",60,6],
				["聖霊救出:極級","聖霊:極",80,6],
				["覚醒の宝珠:一角獣騎士","覚醒:一角",90,0]
      ],
      "水曜ミッション":[
				["空からの贈り物:初級","空贈:初",15,2],
				["空からの贈り物:中級","空贈:中",40,2],
				["空からの贈り物:上級","空贈:上",60,3],
				["空からの贈り物:極級","空贈:極",80,3],
				["男だけの祝杯:初級","男祝:初",15,2],
				["男だけの祝杯:中級","男祝:中",40,2],
				["男だけの祝杯:上級","男祝:上",60,3],
				["男だけの祝杯:極級","男祝:極",80,3],
				["覚醒の宝珠:伝説の海賊","覚醒:海賊",90,0]
      ],
      "木曜ミッション":[
				["新魔水晶の守護者:初級","魔水晶:初",15,4],
				["新魔水晶の守護者:中級","魔水晶:中",30,6],
				["新魔水晶の守護者:上級","魔水晶:上",45,8],
				["新魔水晶の守護者:極級","魔水晶:極",60,8],
				["覚醒の宝珠:怪力少女","覚醒:怪力",90,0]
      ],
      "金曜ミッション":[
				["新魔水晶の守護者:初級","魔水晶:初",15,4],
				["新魔水晶の守護者:中級","魔水晶:中",30,6],
				["新魔水晶の守護者:上級","魔水晶:上",45,8],
				["新魔水晶の守護者:極級","魔水晶:極",60,8],
				["覚醒の宝珠:魔女","覚醒:魔女",90,0]
      ],
      "土曜ミッション":[
        ["覚醒の宝珠:魔導鎧姫","覚醒:魔鎧",90,0],
        ["強者の集う戦場","強者の戦場",90,0]
      ],
      "日曜ミッション":[
        ["強者の集う戦場","強者の戦場",90,0]
      ],
    },
  ],

}
